galahad/__init__.py
galahad/__version__.py
galahad/client.py
galahad/formats.py
galahad/server/__init__.py
galahad/server/annotations.py
galahad/server/classifier.py
galahad/server/config.py
galahad/server/dataclasses.py
galahad/server/server.py
galahad/server/util.py
galahad/server/contrib/__init__.py
galahad/server/contrib/utils.py
galahad/server/contrib/ner/__init__.py
galahad/server/contrib/ner/spacy_ner.py
galahad/server/contrib/pos/__init__.py
galahad/server/contrib/pos/spacy_pos.py
galahad/server/contrib/sentence_classification/__init__.py
galahad/server/contrib/sentence_classification/sklearn_sentence_classifier.py
galahad-0.1.0.dev0.dist-info/METADATA
galahad-0.1.0.dev0.dist-info/WHEEL
galahad-0.1.0.dev0.dist-info/top_level.txt
galahad-0.1.0.dev0.dist-info/RECORD
