Metadata-Version: 2.1
Name: galahad
Version: 0.1.0.dev0
Summary: Machine learning model server that can predict AND train
Home-page: https://github.com/inception-project/inception-external-recommender-v2
Author: Jan-Christoph Klie
Author-email: git@mrklie.com
License: Apache License 2.0
Project-URL: Bug Tracker, https://github.com/inception-project/inception-external-recommender-v2/issues
Project-URL: Documentation, https://github.com/inception-project/inception-external-recommender-v2
Project-URL: Source Code, https://github.com/inception-project/inception-external-recommender-v2
Keywords: inception
Classifier: Development Status :: 4 - Beta
Classifier: Intended Audience :: Developers
Classifier: Intended Audience :: Science/Research
Classifier: License :: OSI Approved :: Apache Software License
Classifier: Programming Language :: Python :: 3 :: Only
Classifier: Programming Language :: Python :: 3.7
Classifier: Programming Language :: Python :: 3.8
Classifier: Programming Language :: Python :: 3.9
Classifier: Programming Language :: Python :: 3.10
Classifier: Topic :: Software Development :: Libraries
Classifier: Topic :: Software Development :: Libraries
Classifier: Topic :: Scientific/Engineering :: Human Machine Interfaces
Classifier: Topic :: Text Processing :: Linguistic
Requires-Python: >=3.7.0
Requires-Dist: fastapi (==0.75.*)
Requires-Dist: uvicorn[standard] (==0.17.*)
Requires-Dist: sortedcontainers (>==2.4.*)
Requires-Dist: joblib (==1.1.*)
Requires-Dist: filelock (==3.6.*)
Requires-Dist: requests (==2.27.*)
Requires-Dist: requests-toolbelt (==0.9.*)
Provides-Extra: all
Requires-Dist: pytest ; extra == 'all'
Requires-Dist: datasets ; extra == 'all'
Requires-Dist: black ; extra == 'all'
Requires-Dist: isort ; extra == 'all'
Requires-Dist: sphinx ; extra == 'all'
Requires-Dist: sphinx-autodoc-typehints ; extra == 'all'
Requires-Dist: sphinx-rtd-theme ; extra == 'all'
Requires-Dist: sphinx-autoapi ; extra == 'all'
Requires-Dist: m2r2 ; extra == 'all'
Requires-Dist: sphinx-copybutton ; extra == 'all'
Requires-Dist: sphinx-rst-builder ; extra == 'all'
Requires-Dist: spacy (==3.2.*) ; extra == 'all'
Requires-Dist: scikit-learn (>=0.24.*) ; extra == 'all'
Requires-Dist: gradio (==2.9.*) ; extra == 'all'
Requires-Dist: nltk (==3.7) ; extra == 'all'
Provides-Extra: contrib
Requires-Dist: spacy (==3.2.*) ; extra == 'contrib'
Requires-Dist: scikit-learn (>=0.24.*) ; extra == 'contrib'
Provides-Extra: demo
Requires-Dist: gradio (==2.9.*) ; extra == 'demo'
Requires-Dist: nltk (==3.7) ; extra == 'demo'
Provides-Extra: dev
Requires-Dist: black ; extra == 'dev'
Requires-Dist: isort ; extra == 'dev'
Provides-Extra: doc
Requires-Dist: sphinx ; extra == 'doc'
Requires-Dist: sphinx-autodoc-typehints ; extra == 'doc'
Requires-Dist: sphinx-rtd-theme ; extra == 'doc'
Requires-Dist: sphinx-autoapi ; extra == 'doc'
Requires-Dist: m2r2 ; extra == 'doc'
Requires-Dist: sphinx-copybutton ; extra == 'doc'
Requires-Dist: sphinx-rst-builder ; extra == 'doc'
Provides-Extra: sklearn
Requires-Dist: scikit-learn (>=0.24.*) ; extra == 'sklearn'
Provides-Extra: spacy
Requires-Dist: spacy (==3.2.*) ; extra == 'spacy'
Provides-Extra: test
Requires-Dist: pytest ; extra == 'test'
Requires-Dist: datasets ; extra == 'test'
